some_student_le/__init__.py
some_student_le/really_not_good.py
some_student_le-1.0.8.dist-info/LICENSE
some_student_le-1.0.8.dist-info/METADATA
some_student_le-1.0.8.dist-info/WHEEL
some_student_le-1.0.8.dist-info/RECORD
