Metadata-Version: 2.1
Name: some-student-le
Version: 1.0.8
Summary: really not good (by Dr Lo, my math teacher)
Author: Taokyle
Author-email: taokyle415@gmail.com
Requires-Python: >=3.8,<4.0
Classifier: Programming Language :: Python :: 3
Classifier: Programming Language :: Python :: 3.8
Classifier: Programming Language :: Python :: 3.9
Classifier: Programming Language :: Python :: 3.10
Classifier: Programming Language :: Python :: 3.11
